{
  "options": {
    "agent_immobilier": ["Vente", "Location", "Gestion locative", "Estimation de bien"],
    "architecte": ["Plan de maison", "Rénovation", "Permis de construire", "Conception d'intérieur"],
    "assistant_maternel": ["Garde d'enfant", "Accueil occasionnel", "Contrat de travail"],
    "avocat": ["Droit civil", "Droit pénal", "Droit des affaires", "Conseil juridique"],
    "carreleur": ["Pose de carrelage", "Carrelage intérieur/extérieur", "Faïence", "Rejointoiement"],
    "charpentier": ["Charpente en bois", "Charpente métallique", "Couverture", "Réparation de toiture"],
    "chauffagiste": ["Installation de chaudière", "Chauffage central", "Pompe à chaleur", "Dépannage"],
    "coiffeur": ["Coupe homme/femme", "Coloration", "Mise en plis", "Soin capillaire"],
    "comptable": ["Tenue de comptabilité", "Conseil fiscal", "Création d'entreprise", "Déclaration de TVA"],
    "cuistot": ["Service traiteur", "Chef à domicile", "Cours de cuisine", "Animation d'événements"],
    "dentiste": ["Consultation générale", "Détartrage", "Blanchiment des dents", "Orthodontie", "Implantologie"],
    "dermatologue": ["Consultation", "Cryothérapie", "Exérèse de lésions", "Cosmétique"],
    "developpeur": ["Développement web", "Application mobile", "Maintenance de site", "Conseil technique"],
    "docteur": ["Médecin généraliste", "Cardiologue", "Pédiatre", "Gynécologue", "Ophtalmologue"],
    "electricien": ["Installation électrique", "Mise aux normes", "Tableau électrique", "Domotique", "Dépannage"],
    "estheticienne": ["Soin du visage", "Épilation", "Manucure/Pédicure", "Maquillage"],
    "garagiste": ["Réparation moteur", "Entretien (vidange)", "Carrosserie", "Contrôle technique"],
    "graphiste": ["Logo", "Charte graphique", "Affiche", "Web design", "Illustration"],
    "infirmier": ["Soins à domicile", "Injections", "Pansements", "Prélèvements sanguins"],
    "jardinier": ["Aménagement de jardin", "Taille de haies", "Tonte de pelouse", "Désherbage"],
    "macon": ["Construction de mur", "Fondations", "Terrassement", "Création d'ouverture"],
    "menuisier": ["Menuiserie intérieure", "Fenêtres", "Portes", "Escalier", "Agencement sur mesure"],
    "opticien": ["Examen de vue", "Monture de lunettes", "Lentilles de contact", "Verres correcteurs"],
    "peintre": ["Peinture intérieure/extérieure", "Préparation des murs", "Pose de papier peint", "Décoration"],
    "pharmacien": ["Pharmacie de garde", "Conseil médical", "Vente de médicaments", "Produits parapharmaceutiques"],
    "plombier": ["Installation sanitaire", "Débouchage de canalisation", "Chauffe-eau", "Fuite d'eau"],
    "psychologue": ["Thérapie individuelle", "Thérapie de couple", "Soutien psychologique", "Bilan psychologique"],
    "serrurier": ["Ouverture de porte", "Changement de serrure", "Pose de blindage", "Coffres-forts"],
    "veterinaire": ["Clinique vétérinaire", "Urgences 24/7", "Vaccination", "Chirurgie", "Toilettage"],
    "webdesigner": ["Maquettage web (UX/UI)", "Design d'interface", "Prototypage", "Audit de site"]
  }
}